{
    "thread": {
        "thread_title": "thread_title",
        "events": [
            {
                "title": "sample_title_1",
                "location": "location",
                "time": "2019",
                "thread_id": "thread_id",
                "tags": [],
            },
            {
                "title": "sample_title_2",
                "location": "location",
                "time": "2019",
                "thread_id": "thread_id",
                "tags": ["projects", "javascript questions"],
            }
        ],
        "comments": [
            {
                "thread_id": "thread_id_1",
                "user_name": "user_name",
                "message": "comment message",
                "mentor_status": true,
                "tags": [],
            },
            {
                "thread_id": "thread_id_2",
                "user_name": "user_name",
                "message": "comment message",
                "mentor_status": false,
                "tags": ["career advice"],
            }
        ],
        "mentors": [
            "name_1",
            "name_2"
        ]
    }
}
